pygoridge/__init__.py
pygoridge/constants.py
pygoridge/exceptions.py
pygoridge/factory.py
pygoridge/json.py
pygoridge/protocol.py
pygoridge/relay.py
pygoridge/rpc.py
pygoridge/socket_relay.py
pygoridge/stream_relay.py
pygoridge/worker.py
pygoridge-0.1.0.dist-info/LICENSE
pygoridge-0.1.0.dist-info/METADATA
pygoridge-0.1.0.dist-info/WHEEL
pygoridge-0.1.0.dist-info/top_level.txt
pygoridge-0.1.0.dist-info/RECORD
