Metadata-Version: 2.1
Name: pygoridge
Version: 0.1.0
Summary: Python-Golang IPC bridge, python client for Goridge
Home-page: https://github.com/atsaero/pygoridge
Author: Maksim Ryndin
Author-email: ryndin@atsaero.ru
License: MIT
Platform: UNKNOWN
Classifier: Development Status :: 4 - Beta
Classifier: Intended Audience :: Developers
Classifier: Intended Audience :: Information Technology
Classifier: Natural Language :: Russian
Classifier: Programming Language :: Python
Classifier: Programming Language :: Python :: 3
Classifier: Programming Language :: Python :: 3.6
Classifier: Programming Language :: Python :: 3.7
Classifier: Programming Language :: Python :: 3.8
Classifier: Programming Language :: Python :: Implementation :: CPython
Classifier: Topic :: Software Development :: Libraries :: Python Modules
Requires-Python: >=3.6
